action_rules/__init__.py
action_rules/action_rules.py
action_rules/candidates/__init__.py
action_rules/candidates/candidate_generator.py
action_rules/cli.py
action_rules/input/__init__.py
action_rules/input/input.py
action_rules/output/__init__.py
action_rules/output/output.py
action_rules/rules/__init__.py
action_rules/rules/rules.py
action_rules-1.0.11.dist-info/LICENSE
action_rules-1.0.11.dist-info/METADATA
action_rules-1.0.11.dist-info/WHEEL
action_rules-1.0.11.dist-info/entry_points.txt
action_rules-1.0.11.dist-info/RECORD
