Metadata-Version: 2.3
Name: action-rules
Version: 1.0.11
Summary: The package for action rules mining using Action-Apriori (Apriori Modified for Action Rules Mining)..
License: MIT
Author: Lukas Sykora
Author-email: lukas.sykora@vse.cz
Requires-Python: >=3.9,<4.0
Classifier: Development Status :: 2 - Pre-Alpha
Classifier: Intended Audience :: Developers
Classifier: License :: OSI Approved :: MIT License
Classifier: Natural Language :: English
Classifier: Programming Language :: Python :: 3
Classifier: Programming Language :: Python :: 3.9
Classifier: Programming Language :: Python :: 3.10
Classifier: Programming Language :: Python :: 3.11
Classifier: Programming Language :: Python :: 3.12
Classifier: Programming Language :: Python :: 3.13
Provides-Extra: dev
Provides-Extra: doc
Provides-Extra: test
Requires-Dist: black (>=24.4.2,<25.0.0) ; extra == "test"
Requires-Dist: bump2version (>=1.0.1,<2.0.0) ; extra == "dev"
Requires-Dist: click (==8.0.1)
Requires-Dist: flake8 (>=7.0.0,<8.0.0) ; extra == "test"
Requires-Dist: flake8-docstrings (>=1.7.0,<2.0.0) ; extra == "test"
Requires-Dist: isort (>=5.13.2,<6.0.0) ; extra == "test"
Requires-Dist: mkdocs (>=1.6.0,<2.0.0) ; extra == "doc"
Requires-Dist: mkdocs-autorefs (>=1.0.1,<2.0.0) ; extra == "doc"
Requires-Dist: mkdocs-include-markdown-plugin (>=6.1.1,<7.0.0) ; extra == "doc"
Requires-Dist: mkdocs-material (>=9.5.25,<10.0.0) ; extra == "doc"
Requires-Dist: mkdocstrings (>=0.25.1,<0.26.0) ; extra == "doc"
Requires-Dist: mkdocstrings-python (>=1.10.3,<2.0.0)
Requires-Dist: mypy (>=1.10.0,<2.0.0) ; extra == "test"
Requires-Dist: pandas (>=2.2.2,<3.0.0)
Requires-Dist: pip (>=24.0,<25.0) ; extra == "dev"
Requires-Dist: pre-commit (>=3.7.1,<4.0.0) ; extra == "dev"
Requires-Dist: pytest (>=8.2.1,<9.0.0) ; extra == "test"
Requires-Dist: pytest-cov (>=5.0.0,<6.0.0) ; extra == "test"
Requires-Dist: toml (>=0.10.2,<0.11.0) ; extra == "dev"
Requires-Dist: tox (>=4.15.0,<5.0.0) ; extra == "dev"
Requires-Dist: twine (>=5.1.0,<6.0.0) ; extra == "dev"
Requires-Dist: virtualenv (>=20.26.2,<21.0.0) ; extra == "dev"
Project-URL: Homepage, https://github.com/lukassykora/action-rules
